walide/__init__.py
walide/crossover.py
walide/de.py
walide/fitness.py
walide/generator.py
walide/mutate.py
walide/selection.py
walide-0.3.1.dist-info/licenses/LICENSE.txt
walide-0.3.1.dist-info/METADATA
walide-0.3.1.dist-info/WHEEL
walide-0.3.1.dist-info/top_level.txt
walide-0.3.1.dist-info/RECORD
